MANIFEST.in
README.md
setup.cfg
setup.py
uwosh.portaltabssearchbox-configure.zcml
docs/HISTORY.txt
docs/INSTALL.txt
docs/LICENSE.GPL
docs/LICENSE.txt
uwosh/__init__.py
uwosh.portaltabssearchbox.egg-info/PKG-INFO
uwosh.portaltabssearchbox.egg-info/SOURCES.txt
uwosh.portaltabssearchbox.egg-info/SOURCES.txt~
uwosh.portaltabssearchbox.egg-info/dependency_links.txt
uwosh.portaltabssearchbox.egg-info/entry_points.txt
uwosh.portaltabssearchbox.egg-info/namespace_packages.txt
uwosh.portaltabssearchbox.egg-info/not-zip-safe
uwosh.portaltabssearchbox.egg-info/requires.txt
uwosh.portaltabssearchbox.egg-info/top_level.txt
uwosh/portaltabssearchbox/.DS_Store
uwosh/portaltabssearchbox/__init__.py
uwosh/portaltabssearchbox/configure.zcml
uwosh/portaltabssearchbox/profiles.zcml
uwosh/portaltabssearchbox/setuphandlers.py
uwosh/portaltabssearchbox/skins.zcml
uwosh/portaltabssearchbox/tests.py
uwosh/portaltabssearchbox/version.txt
uwosh/portaltabssearchbox/browser/__init__.py
uwosh/portaltabssearchbox/browser/configure.zcml
uwosh/portaltabssearchbox/browser/interfaces.py
uwosh/portaltabssearchbox/browser/viewlet.pt
uwosh/portaltabssearchbox/browser/viewlets.py
uwosh/portaltabssearchbox/browser/images/README.txt
uwosh/portaltabssearchbox/browser/stylesheets/README.txt
uwosh/portaltabssearchbox/browser/stylesheets/main.css
uwosh/portaltabssearchbox/locales/README.txt
uwosh/portaltabssearchbox/profiles/default/cssregistry.xml
uwosh/portaltabssearchbox/profiles/default/jsregistry.xml
uwosh/portaltabssearchbox/profiles/default/metadata.xml
uwosh/portaltabssearchbox/profiles/default/skins.xml
uwosh/portaltabssearchbox/profiles/default/uwosh.portaltabssearchbox_various.txt
uwosh/portaltabssearchbox/profiles/default/viewlets.xml
uwosh/portaltabssearchbox/profiles/uninstall/viewlets.xml
uwosh/portaltabssearchbox/skins/uwosh_portaltabssearchbox_custom_images/CONTENT.txt
uwosh/portaltabssearchbox/skins/uwosh_portaltabssearchbox_custom_templates/CONTENT.txt
uwosh/portaltabssearchbox/skins/uwosh_portaltabssearchbox_styles/CONTENT.txt
uwosh/portaltabssearchbox/skins/uwosh_portaltabssearchbox_styles/base_properties.props