Metadata-Version: 1.1
Name: uwosh.portaltabssearchbox
Version: 0.1.10
Summary: moves search box into portal tabs
Home-page: http://plone.org/products/uwosh.portaltabssearchbox
Author: T. Kim Nguyen
Author-email: nguyen@uwosh.edu
License: GPL
Keywords: portal tabs,search box,viewlet
Platform: UNKNOWN
Classifier: Framework :: Plone
Classifier: Programming Language :: Python
